[
    {
        "name": "Brad Phillips",
        "lastDay": "2019-01-04 17:00",
        "comingFrom": "Goodlife",
        "goingTo": "Carfax"
    },
    {
        "name": "Mathew Manton",
        "lastDay": "2019-02-15 17:00",
        "comingFrom": "Goodlife",
        "goingTo": "Carfax"
    },
    {
        "name": "Adela Salkic",
        "lastDay": "2019-03-19 17:00",
        "comingFrom": "Goodlife",
        "goingTo": "Carfax"
    },
    {
        "name": "Werner Uetz",
        "lastDay": "2019-04-12 17:00",
        "comingFrom": "Goodlife",
        "goingTo": "Carfax"
    },
    {
        "name": "Tyson Seaborn",
        "lastDay": "2019-05-03 17:00",
        "comingFrom": "Goodlife",
        "goingTo": "Autodata Solutions"
    },
    {
        "name": "Connor Montag",
        "lastDay": "2019-05-10 17:00",
        "comingFrom": "Goodlife",
        "goingTo": "Carfax"
    },
    {
        "name": "Sean Arts",
        "lastDay": "2019-06-06 15:50",
        "comingFrom": "Goodlife",
        "goingTo": "Carfax"
    },
    {
        "name": "Kyle DeGaust",
        "lastDay": "2019-06-07 15:05",
        "comingFrom": "Goodlife",
        "goingTo": "Carfax"
    },
    {
        "name": "Philip Craig",
        "lastDay": "2019-07-12 15:00",
        "comingFrom": "Goodlife",
        "goingTo": "Carfax"
    },
    {
        "name": "Brandon Sheppard",
        "lastDay": "2019-08-06 17:00",
        "comingFrom": "Goodlife",
        "goingTo": "Leven Systems"
    },
    {
        "name": "Chris Frank",
        "lastDay": "2019-10-10 17:00",
        "comingFrom": "Goodlife",
        "goingTo": "..."
    },
    {
        "name": "Mathew Manton",
        "lastDay": "2019-10-15 17:00",
        "comingFrom": "Carfax",
        "goingTo": "Two Hat"
    },
    {
        "name": "Jeremy Winter",
        "lastDay": "2019-10-24 17:00",
        "comingFrom": "Goodlife",
        "goingTo": "Carfax"
    },
    {
        "name": "Dan Balint",
        "lastDay": "2019-10-24 17:00",
        "comingFrom": "Goodlife",
        "goingTo": "Zouling"
    },
    {
        "name": "Anthony Heinrichs",
        "lastDay": "2019-10-31 17:00",
        "comingFrom": "Goodlife",
        "goingTo": "Europe"
    },
    {
        "name": "Mike Marsman",
        "lastDay": "2019-11-12 17:00",
        "comingFrom": "Goodlife",
        "goingTo": "..."
    },
    {
        "name": "James Betterley",
        "lastDay": "2019-11-12 17:00",
        "comingFrom": "Goodlife",
        "goingTo": "..."
    },
    {
        "name": "Lindsay Robbins",
        "lastDay": "2019-11-15 17:00",
        "comingFrom": "Goodlife",
        "goingTo": "Carfax"
    },
    {
        "name": "Sunny Chunilall",
        "lastDay": "2019-11-28 17:00",
        "comingFrom": "Goodlife",
        "goingTo": ":("
    },
    {
        "name": "Maurice Sewell",
        "lastDay": "2019-12-27 17:00",
        "comingFrom": "Goodlife",
        "goingTo": "StarTech"
    },
    {
        "name": "Meagan Murray",
        "lastDay": "2019-12-27 17:00",
        "comingFrom": "Goodlife",
        "goingTo": "CanadaLife"
    },
    {
        "name": "Steve Groves",
        "lastDay": "2020-01-24 17:00",
        "comingFrom": "Goodlife",
        "goingTo": "Start.ca"
    },
    {
        "name": "David Brad",
        "lastDay": "2020-01-31 17:00",
        "comingFrom": "Goodlife",
        "goingTo": "Binnj"
    },
    {
        "name": "Bradley Elliott",
        "lastDay": "2020-01-31 17:00",
        "comingFrom": "Goodlife",
        "goingTo": "Binnj"
    },
    {
        "name": "James Betterley",
        "lastDay": "2020-01-12 17:00",
        "comingFrom": "...",
        "goingTo": "Two Hat"
    },
    {
        "name": "Joshua Geurts",
        "lastDay": "2020-01-31 17:00",
        "comingFrom": "Goodlife",
        "goingTo": "Ophardt Hygiene"
    },
    {
        "name": "Alexander Smith",
        "lastDay": "2020-01-31 17:00",
        "comingFrom": "Goodlife",
        "goingTo": "Carfax"
    },
    {
        "name": "Shikha Singh",
        "lastDay": "2020-02-05 17:00",
        "comingFrom": "Goodlife",
        "goingTo": "Carfax"
    },
    {
        "name": "David Leonard",
        "lastDay": "2020-02-20 17:00",
        "comingFrom": "Goodlife",
        "goingTo": "Carfax"
    },
    {
        "name": "Dan Denunzio",
        "lastDay": "2020-02-28 17:00",
        "comingFrom": "Goodlife",
        "goingTo": "Precision Nutrition"
    },
    {
        "name": "James Betterley",
        "lastDay": "2020-02-28 17:00",
        "comingFrom": "Two Hat",
        "goingTo": "Binnj"
    },
    {
        "name": "Steven Avery",
        "lastDay": "2020-02-28 17:00",
        "comingFrom": "Goodlife",
        "goingTo": "Binnj"
    },
    {
        "name": "Kevin Donde",
        "lastDay": "2020-02-21 17:00",
        "comingFrom": "Goodlife",
        "goingTo": "..."
    },
    {
        "name": "Kevin Donde",
        "lastDay": "2020-03-21 17:00",
        "comingFrom": "...",
        "goingTo": "Two Hat"
    },
    {
        "name": "Adam Carr",
        "lastDay": "2020-05-22 17:00",
        "comingFrom": "Goodlife",
        "goingTo": "Start.ca"
    },
    {
        "name": "Noorain Adeeb",
        "lastDay": "2020-05-28 17:00",
        "comingFrom": "Goodlife",
        "goingTo": "Start.ca"
    },
    {
        "name": "Mike McRorie",
        "lastDay": "2020-07-05 17:00",
        "comingFrom": "Goodlife",
        "goingTo": "CanadaLife"
    },
    {
        "name": "Derek Brown",
        "lastDay": "2020-08-14 17:00",
        "comingFrom": "Goodlife",
        "goingTo": "Improbable.io"
    },
    {
        "name": "Spencer Milmine",
        "lastDay": "2020-08-14 17:00",
        "comingFrom": "Goodlife",
        "goingTo": "Carfax"
    },
    {
        "name": "Mathew Manton",
        "lastDay": "2020-11-15 17:00",
        "comingFrom": "Two Hat",
        "goingTo": "..."
    },
    {
        "name": "Dima Nabhani",
        "lastDay": "2021-02-16 17:00",
        "comingFrom": "Goodlife",
        "goingTo": "Vitruvi Software"
    },
    {
        "name": "Jaenuz Gorospe",
        "lastDay": "2021-01-29 17:00",
        "comingFrom": "Goodlife",
        "goingTo": "Binnj"
    },
    {
        "name": "David Cosman",
        "lastDay": "2021-03-29 17:00",
        "comingFrom": "Goodlife",
        "goingTo": "Two Hat"
    },
    {
        "name": "Brooke Herbert",
        "lastDay": "2021-04-21 17:00",
        "comingFrom": "Goodlife",
        "goingTo": "Carfax"
    },
    {
        "name": "Chris Janes",
        "lastDay": "2021-05-07 17:00",
        "comingFrom": "Goodlife",
        "goingTo": "interVal"
    },
    {
        "name": "Andrew McFalls",
        "lastDay": "2021-05-15 17:00",
        "comingFrom": "Goodlife",
        "goingTo": "Carfax"
    },
    {
        "name": "David Brad",
        "lastDay": "2021-06-16 17:00",
        "comingFrom": "Binnj",
        "goingTo": "Carfax"
    },
    {
        "name": "Adam Carr",
        "lastDay": "2021-06-22 17:00",
        "comingFrom": "Start.ca",
        "goingTo": "Fit4Less"
    },
    {
        "name": "Mathew Manton",
        "lastDay": "2021-06-15 17:00",
        "comingFrom": "...",
        "goingTo": "Hyper Hippo"
    },
    {
        "name": "Kevin Donde",
        "lastDay": "2021-09-21 17:00",
        "comingFrom": "Two Hat",
        "goingTo": "Carfax"
    },
    {
        "name": "Trevor Horman",
        "lastDay": "2021-09-24 17:00",
        "comingFrom": "Goodlife",
        "goingTo": "interVal"
    },
    {
        "name": "James Betterley",
        "lastDay": "2021-11-28 17:00",
        "comingFrom": "Binnj",
        "goingTo": "Geotab"
    },
    {
        "name": "Jon Pilon",
        "lastDay": "2021-12-24 12:00",
        "comingFrom": "Goodlife",
        "goingTo": "Dell/Alienware"
    },
    {
        "name": "Steven Avery",
        "lastDay": "2020-01-24 17:00",
        "comingFrom": "Binnj",
        "goingTo": "Carfax"
    },
    {
        "name": "Brooke Herbert",
        "lastDay": "2022-03-24 17:00",
        "comingFrom": "Carfax",
        "goingTo": "Geotab"
    },
    {
        "name": "Andrew McFalls",
        "lastDay": "2022-03-27 17:00",
        "comingFrom": "Carfax",
        "goingTo": "Goodlife"
    },
    {
        "name": "Tibi Egyed",
        "lastDay": "2022-03-18 12:00",
        "comingFrom": "Carfax",
        "goingTo": "Coinbase"
    },
    {
        "name": "Jeremy Winter",
        "lastDay": "2022-04-14 12:00",
        "comingFrom": "Carfax",
        "goingTo": "SailPoint"
    },
    {
        "name": "Don Nickle",
        "lastDay": "2022-04-22 12:00",
        "comingFrom": "Carfax",
        "goingTo": "Vena"
    },
    {
        "name": "Phil Craig",
        "lastDay": "2022-04-22 12:00",
        "comingFrom": "Carfax",
        "goingTo": "SailPoint"
    },
    {
        "name": "Kris Hartzke",
        "lastDay": "2022-05-02 12:00",
        "comingFrom": "Carfax",
        "goingTo": "SailPoint"
    },
    {
        "name": "Ryan Picanco",
        "lastDay": "2022-05-06 12:00",
        "comingFrom": "Carfax",
        "goingTo": "SailPoint"
    },
    {
        "name": "Joel Kennedy",
        "lastDay": "2022-05-09 12:00",
        "comingFrom": "Carfax",
        "goingTo": "Meta"
    }
]
